Workbook

Sheet analytics_mart
A1: Год | B1: Выручка | C1: Себестоимость продаж | D1: Валовая прибыль | E1: Прибыль от продаж | F1: Прибыль до налогообложения | G1: Чистая прибыль | H1: Активы всего | I1: Внеоборотные активы | J1: Оборотные активы | K1: Капитал и резервы | L1: Долгосрочные обязательства | M1: Краткосрочные обязательства | N1: Денежные средства и эквиваленты | O1: Дебиторская задолженность | P1: Кредиторская задолженность | Q1: Запасы | R1: Обязательства всего | S1: Чистый оборотный капитал | T1: Средние активы | U1: Средний капитал | V1: Средняя дебиторская задолженность | W1: Валовая маржа | X1: Маржа продаж | Y1: Чистая маржа | Z1: Рентабельность активов | AA1: Рентабельность собственного капитала | AB1: Коэффициент текущей ликвидности | AC1: Коэффициент быстрой ликвидности | AD1: Коэффициент абсолютной ликвидности | AE1: Коэффициент автономии | AF1: Соотношение обязательств и капитала | AG1: Доля обязательств в активах | AH1: Оборачиваемость активов | AI1: Период погашения дебиторской задолженности, дней | AJ1: Темп роста выручки | AK1: Темп роста чистой прибыли | AL1: Темп роста активов
A2: 2020 | B2: =SUMIFS(clean_financials_2020_2025!$D:$D,clean_financials_2020_2025!$C:$C,$A2,clean_financials_2020_2025!$B:$B,2110,clean_financials_2020_2025!$E:$E,"income_statement") -> 2536151 | C2: =SUMIFS(clean_financials_2020_2025!$D:$D,clean_financials_2020_2025!$C:$C,$A2,clean_financials_2020_2025!$B:$B,2120,clean_financials_2020_2025!$E:$E,"income_statement") -> -794444 | D2: =SUMIFS(clean_financials_2020_2025!$D:$D,clean_financials_2020_2025!$C:$C,$A2,clean_financials_2020_2025!$B:$B,2100,clean_financials_2020_2025!$E:$E,"income_statement") -> 1741707 | E2: =SUMIFS(clean_financials_2020_2025!$D:$D,clean_financials_2020_2025!$C:$C,$A2,clean_financials_2020_2025!$B:$B,2200,clean_financials_2020_2025!$E:$E,"income_statement") -> 1062847 | F2: =SUMIFS(clean_financials_2020_2025!$D:$D,clean_financials_2020_2025!$C:$C,$A2,clean_financials_2020_2025!$B:$B,2300,clean_financials_2020_2025!$E:$E,"income_statement") -> 1271085 | G2: =SUMIFS(clean_financials_2020_2025!$D:$D,clean_financials_2020_2025!$C:$C,$A2,clean_financials_2020_2025!$B:$B,2400,clean_financials_2020_2025!$E:$E,"income_statement") -> 1031538 | H2: =SUMIFS(clean_financials_2020_2025!$D:$D,clean_financials_2020_2025!$C:$C,$A2,clean_financials_2020_2025!$B:$B,1600,clean_financials_2020_2025!$E:$E,"balance") -> 3018985 | I2: =SUMIFS(clean_financials_2020_2025!$D:$D,clean_financials_2020_2025!$C:$C,$A2,clean_financials_2020_2025!$B:$B,1100,clean_financials_2020_2025!$E:$E,"balance") -> 268300 | J2: =SUMIFS(clean_financials_2020_2025!$D:$D,clean_financials_2020_2025!$C:$C,$A2,clean_financials_2020_2025!$B:$B,1200,clean_financials_2020_2025!$E:$E,"balance") -> 2750685 | K2: =SUMIFS(clean_financials_2020_2025!$D:$D,clean_financials_2020_2025!$C:$C,$A2,clean_financials_2020_2025!$B:$B,1300,clean_financials_2020_2025!$E:$E,"balance") -> 2957634 | L2: =SUMIFS(clean_financials_2020_2025!$D:$D,clean_financials_2020_2025!$C:$C,$A2,clean_financials_2020_2025!$B:$B,1400,clean_financials_2020_2025!$E:$E,"balance") -> 230 | M2: =SUMIFS(clean_financials_2020_2025!$D:$D,clean_financials_2020_2025!$C:$C,$A2,clean_financials_2020_2025!$B:$B,1500,clean_financials_2020_2025!$E:$E,"balance") -> 61121 | N2: =SUMIFS(clean_financials_2020_2025!$D:$D,clean_financials_2020_2025!$C:$C,$A2,clean_financials_2020_2025!$B:$B,1250,clean_financials_2020_2025!$E:$E,"balance") -> 1302369 | O2: =SUMIFS(clean_financials_2020_2025!$D:$D,clean_financials_2020_2025!$C:$C,$A2,clean_financials_2020_2025!$B:$B,1230,clean_financials_2020_2025!$E:$E,"balance") -> 259411 | P2: =SUMIFS(clean_financials_2020_2025!$D:$D,clean_financials_2020_2025!$C:$C,$A2,clean_financials_2020_2025!$B:$B,1520,clean_financials_2020_2025!$E:$E,"balance") -> 31177 | Q2: =SUMIFS(clean_financials_2020_2025!$D:$D,clean_financials_2020_2025!$C:$C,$A2,clean_financials_2020_2025!$B:$B,1210,clean_financials_2020_2025!$E:$E,"balance") -> 425 | R2: =L2+M2 -> 61351 | S2: =J2-M2 -> 2689564 | T2: ="" | U2: ="" | V2: ="" | W2: =IFERROR(D2/B2,"") -> 0.68675209 | X2: =IFERROR(E2/B2,"") -> 0.41907875 | Y2: =IFERROR(G2/B2,"") -> 0.40673367 | Z2: ="" | AA2: ="" | AB2: =IFERROR(J2/M2,"") -> 45.003927 | AC2: =IFERROR((J2-Q2)/M2,"") -> 44.996973 | AD2: =IFERROR(N2/M2,"") -> 21.308045 | AE2: =IFERROR(K2/H2,"") -> 0.97967827 | AF2: =IFERROR(R2/K2,"") -> 0.02074327 | AG2: =IFERROR(R2/H2,"") -> 0.020321731 | AH2: ="" | AI2: ="" | AJ2: ="" | AK2: ="" | AL2: =""
A3: 2021 | B3: =SUMIFS(clean_financials_2020_2025!$D:$D,clean_financials_2020_2025!$C:$C,$A3,clean_financials_2020_2025!$B:$B,2110,clean_financials_2020_2025!$E:$E,"income_statement") -> 2532640 | C3: =SUMIFS(clean_financials_2020_2025!$D:$D,clean_financials_2020_2025!$C:$C,$A3,clean_financials_2020_2025!$B:$B,2120,clean_financials_2020_2025!$E:$E,"income_statement") -> -650710 | D3: =SUMIFS(clean_financials_2020_2025!$D:$D,clean_financials_2020_2025!$C:$C,$A3,clean_financials_2020_2025!$B:$B,2100,clean_financials_2020_2025!$E:$E,"income_statement") -> 1881930 | E3: =SUMIFS(clean_financials_2020_2025!$D:$D,clean_financials_2020_2025!$C:$C,$A3,clean_financials_2020_2025!$B:$B,2200,clean_financials_2020_2025!$E:$E,"income_statement") -> 977340 | F3: =SUMIFS(clean_financials_2020_2025!$D:$D,clean_financials_2020_2025!$C:$C,$A3,clean_financials_2020_2025!$B:$B,2300,clean_financials_2020_2025!$E:$E,"income_statement") -> 1083067 | G3: =SUMIFS(clean_financials_2020_2025!$D:$D,clean_financials_2020_2025!$C:$C,$A3,clean_financials_2020_2025!$B:$B,2400,clean_financials_2020_2025!$E:$E,"income_statement") -> 1033647 | H3: =SUMIFS(clean_financials_2020_2025!$D:$D,clean_financials_2020_2025!$C:$C,$A3,clean_financials_2020_2025!$B:$B,1600,clean_financials_2020_2025!$E:$E,"balance") -> 4445733 | I3: =SUMIFS(clean_financials_2020_2025!$D:$D,clean_financials_2020_2025!$C:$C,$A3,clean_financials_2020_2025!$B:$B,1100,clean_financials_2020_2025!$E:$E,"balance") -> 343275 | J3: =SUMIFS(clean_financials_2020_2025!$D:$D,clean_financials_2020_2025!$C:$C,$A3,clean_financials_2020_2025!$B:$B,1200,clean_financials_2020_2025!$E:$E,"balance") -> 4102458 | K3: =SUMIFS(clean_financials_2020_2025!$D:$D,clean_financials_2020_2025!$C:$C,$A3,clean_financials_2020_2025!$B:$B,1300,clean_financials_2020_2025!$E:$E,"balance") -> 3975662 | L3: =SUMIFS(clean_financials_2020_2025!$D:$D,clean_financials_2020_2025!$C:$C,$A3,clean_financials_2020_2025!$B:$B,1400,clean_financials_2020_2025!$E:$E,"balance") -> 153735 | M3: =SUMIFS(clean_financials_2020_2025!$D:$D,clean_financials_2020_2025!$C:$C,$A3,clean_financials_2020_2025!$B:$B,1500,clean_financials_2020_2025!$E:$E,"balance") -> 316336 | N3: =SUMIFS(clean_financials_2020_2025!$D:$D,clean_financials_2020_2025!$C:$C,$A3,clean_financials_2020_2025!$B:$B,1250,clean_financials_2020_2025!$E:$E,"balance") -> 2484861 | O3: =SUMIFS(clean_financials_2020_2025!$D:$D,clean_financials_2020_2025!$C:$C,$A3,clean_financials_2020_2025!$B:$B,1230,clean_financials_2020_2025!$E:$E,"balance") -> 626083 | P3: =SUMIFS(clean_financials_2020_2025!$D:$D,clean_financials_2020_2025!$C:$C,$A3,clean_financials_2020_2025!$B:$B,1520,clean_financials_2020_2025!$E:$E,"balance") -> 286098 | Q3: =SUMIFS(clean_financials_2020_2025!$D:$D,clean_financials_2020_2025!$C:$C,$A3,clean_financials_2020_2025!$B:$B,1210,clean_financials_2020_2025!$E:$E,"balance") -> 31 | R3: =L3+M3 -> 470071 | S3: =J3-M3 -> 3786122 | T3: =(H3+H2)/2 -> 3732359 | U3: =(K3+K2)/2 -> 3466648 | V3: =(O3+O2)/2 -> 442747 | W3: =IFERROR(D3/B3,"") -> 0.74307047 | X3: =IFERROR(E3/B3,"") -> 0.38589772 | Y3: =IFERROR(G3/B3,"") -> 0.40813025 | Z3: =IFERROR(G3/T3,"") -> 0.27694201 | AA3: =IFERROR(G3/U3,"") -> 0.29816901 | AB3: =IFERROR(J3/M3,"") -> 12.968673 | AC3: =IFERROR((J3-Q3)/M3,"") -> 12.968575 | AD3: =IFERROR(N3/M3,"") -> 7.8551319 | AE3: =IFERROR(K3/H3,"") -> 0.89426468 | AF3: =IFERROR(R3/K3,"") -> 0.11823716 | AG3: =IFERROR(R3/H3,"") -> 0.10573532 | AH3: =IFERROR(B3/T3,"") -> 0.67856281 | AI3: =IFERROR(V3/B3*365,"") -> 63.807985 | AJ3: =IFERROR(B3/B2-1,"") -> -0.0013843813 | AK3: =IFERROR(G3/G2-1,"") -> 0.0020445199 | AL3: =IFERROR(H3/H2-1,"") -> 0.47259195
A4: 2022 | B4: =SUMIFS(clean_financials_2020_2025!$D:$D,clean_financials_2020_2025!$C:$C,$A4,clean_financials_2020_2025!$B:$B,2110,clean_financials_2020_2025!$E:$E,"income_statement") -> 2541046 | C4: =SUMIFS(clean_financials_2020_2025!$D:$D,clean_financials_2020_2025!$C:$C,$A4,clean_financials_2020_2025!$B:$B,2120,clean_financials_2020_2025!$E:$E,"income_statement") -> -521123 | D4: =SUMIFS(clean_financials_2020_2025!$D:$D,clean_financials_2020_2025!$C:$C,$A4,clean_financials_2020_2025!$B:$B,2100,clean_financials_2020_2025!$E:$E,"income_statement") -> 2019923 | E4: =SUMIFS(clean_financials_2020_2025!$D:$D,clean_financials_2020_2025!$C:$C,$A4,clean_financials_2020_2025!$B:$B,2200,clean_financials_2020_2025!$E:$E,"income_statement") -> 770995 | F4: =SUMIFS(clean_financials_2020_2025!$D:$D,clean_financials_2020_2025!$C:$C,$A4,clean_financials_2020_2025!$B:$B,2300,clean_financials_2020_2025!$E:$E,"income_statement") -> 126902 | G4: =SUMIFS(clean_financials_2020_2025!$D:$D,clean_financials_2020_2025!$C:$C,$A4,clean_financials_2020_2025!$B:$B,2400,clean_financials_2020_2025!$E:$E,"income_statement") -> -427987 | H4: =SUMIFS(clean_financials_2020_2025!$D:$D,clean_financials_2020_2025!$C:$C,$A4,clean_financials_2020_2025!$B:$B,1600,clean_financials_2020_2025!$E:$E,"balance") -> 3969858 | I4: =SUMIFS(clean_financials_2020_2025!$D:$D,clean_financials_2020_2025!$C:$C,$A4,clean_financials_2020_2025!$B:$B,1100,clean_financials_2020_2025!$E:$E,"balance") -> 288795 | J4: =SUMIFS(clean_financials_2020_2025!$D:$D,clean_financials_2020_2025!$C:$C,$A4,clean_financials_2020_2025!$B:$B,1200,clean_financials_2020_2025!$E:$E,"balance") -> 3681063 | K4: =SUMIFS(clean_financials_2020_2025!$D:$D,clean_financials_2020_2025!$C:$C,$A4,clean_financials_2020_2025!$B:$B,1300,clean_financials_2020_2025!$E:$E,"balance") -> 3557540 | L4: =SUMIFS(clean_financials_2020_2025!$D:$D,clean_financials_2020_2025!$C:$C,$A4,clean_financials_2020_2025!$B:$B,1400,clean_financials_2020_2025!$E:$E,"balance") -> 132813 | M4: =SUMIFS(clean_financials_2020_2025!$D:$D,clean_financials_2020_2025!$C:$C,$A4,clean_financials_2020_2025!$B:$B,1500,clean_financials_2020_2025!$E:$E,"balance") -> 279505 | N4: =SUMIFS(clean_financials_2020_2025!$D:$D,clean_financials_2020_2025!$C:$C,$A4,clean_financials_2020_2025!$B:$B,1250,clean_financials_2020_2025!$E:$E,"balance") -> 1034196 | O4: =SUMIFS(clean_financials_2020_2025!$D:$D,clean_financials_2020_2025!$C:$C,$A4,clean_financials_2020_2025!$B:$B,1230,clean_financials_2020_2025!$E:$E,"balance") -> 1553374 | P4: =SUMIFS(clean_financials_2020_2025!$D:$D,clean_financials_2020_2025!$C:$C,$A4,clean_financials_2020_2025!$B:$B,1520,clean_financials_2020_2025!$E:$E,"balance") -> 237311 | Q4: =SUMIFS(clean_financials_2020_2025!$D:$D,clean_financials_2020_2025!$C:$C,$A4,clean_financials_2020_2025!$B:$B,1210,clean_financials_2020_2025!$E:$E,"balance") -> 2936 | R4: =L4+M4 -> 412318 | S4: =J4-M4 -> 3401558 | T4: =(H4+H3)/2 -> 4207795.5 | U4: =(K4+K3)/2 -> 3766601 | V4: =(O4+O3)/2 -> 1089728.5 | W4: =IFERROR(D4/B4,"") -> 0.79491792 | X4: =IFERROR(E4/B4,"") -> 0.30341639 | Y4: =IFERROR(G4/B4,"") -> -0.16842946 | Z4: =IFERROR(G4/T4,"") -> -0.10171288 | AA4: =IFERROR(G4/U4,"") -> -0.11362685 | AB4: =IFERROR(J4/M4,"") -> 13.169936 | AC4: =IFERROR((J4-Q4)/M4,"") -> 13.159432 | AD4: =IFERROR(N4/M4,"") -> 3.7000984 | AE4: =IFERROR(K4/H4,"") -> 0.89613785 | AF4: =IFERROR(R4/K4,"") -> 0.11589975 | AG4: =IFERROR(R4/H4,"") -> 0.10386215 | AH4: =IFERROR(B4/T4,"") -> 0.60389009 | AI4: =IFERROR(V4/B4*365,"") -> 156.53038 | AJ4: =IFERROR(B4/B3-1,"") -> 0.0033190663 | AK4: =IFERROR(G4/G3-1,"") -> -1.4140553 | AL4: =IFERROR(H4/H3-1,"") -> -0.10704084
A5: 2023 | B5: =SUMIFS(clean_financials_2020_2025!$D:$D,clean_financials_2020_2025!$C:$C,$A5,clean_financials_2020_2025!$B:$B,2110,clean_financials_2020_2025!$E:$E,"income_statement") -> 3123853 | C5: =SUMIFS(clean_financials_2020_2025!$D:$D,clean_financials_2020_2025!$C:$C,$A5,clean_financials_2020_2025!$B:$B,2120,clean_financials_2020_2025!$E:$E,"income_statement") -> -260366 | D5: =SUMIFS(clean_financials_2020_2025!$D:$D,clean_financials_2020_2025!$C:$C,$A5,clean_financials_2020_2025!$B:$B,2100,clean_financials_2020_2025!$E:$E,"income_statement") -> 2863487 | E5: =SUMIFS(clean_financials_2020_2025!$D:$D,clean_financials_2020_2025!$C:$C,$A5,clean_financials_2020_2025!$B:$B,2200,clean_financials_2020_2025!$E:$E,"income_statement") -> 736690 | F5: =SUMIFS(clean_financials_2020_2025!$D:$D,clean_financials_2020_2025!$C:$C,$A5,clean_financials_2020_2025!$B:$B,2300,clean_financials_2020_2025!$E:$E,"income_statement") -> 938020 | G5: =SUMIFS(clean_financials_2020_2025!$D:$D,clean_financials_2020_2025!$C:$C,$A5,clean_financials_2020_2025!$B:$B,2400,clean_financials_2020_2025!$E:$E,"income_statement") -> 762196 | H5: =SUMIFS(clean_financials_2020_2025!$D:$D,clean_financials_2020_2025!$C:$C,$A5,clean_financials_2020_2025!$B:$B,1600,clean_financials_2020_2025!$E:$E,"balance") -> 3983498 | I5: =SUMIFS(clean_financials_2020_2025!$D:$D,clean_financials_2020_2025!$C:$C,$A5,clean_financials_2020_2025!$B:$B,1100,clean_financials_2020_2025!$E:$E,"balance") -> 743254 | J5: =SUMIFS(clean_financials_2020_2025!$D:$D,clean_financials_2020_2025!$C:$C,$A5,clean_financials_2020_2025!$B:$B,1200,clean_financials_2020_2025!$E:$E,"balance") -> 3240244 | K5: =SUMIFS(clean_financials_2020_2025!$D:$D,clean_financials_2020_2025!$C:$C,$A5,clean_financials_2020_2025!$B:$B,1300,clean_financials_2020_2025!$E:$E,"balance") -> 3144989 | L5: =SUMIFS(clean_financials_2020_2025!$D:$D,clean_financials_2020_2025!$C:$C,$A5,clean_financials_2020_2025!$B:$B,1400,clean_financials_2020_2025!$E:$E,"balance") -> 590089 | M5: =SUMIFS(clean_financials_2020_2025!$D:$D,clean_financials_2020_2025!$C:$C,$A5,clean_financials_2020_2025!$B:$B,1500,clean_financials_2020_2025!$E:$E,"balance") -> 248420 | N5: =SUMIFS(clean_financials_2020_2025!$D:$D,clean_financials_2020_2025!$C:$C,$A5,clean_financials_2020_2025!$B:$B,1250,clean_financials_2020_2025!$E:$E,"balance") -> 42327 | O5: =SUMIFS(clean_financials_2020_2025!$D:$D,clean_financials_2020_2025!$C:$C,$A5,clean_financials_2020_2025!$B:$B,1230,clean_financials_2020_2025!$E:$E,"balance") -> 2333028 | P5: =SUMIFS(clean_financials_2020_2025!$D:$D,clean_financials_2020_2025!$C:$C,$A5,clean_financials_2020_2025!$B:$B,1520,clean_financials_2020_2025!$E:$E,"balance") -> 190284 | Q5: =SUMIFS(clean_financials_2020_2025!$D:$D,clean_financials_2020_2025!$C:$C,$A5,clean_financials_2020_2025!$B:$B,1210,clean_financials_2020_2025!$E:$E,"balance") -> 2238 | R5: =L5+M5 -> 838509 | S5: =J5-M5 -> 2991824 | T5: =(H5+H4)/2 -> 3976678 | U5: =(K5+K4)/2 -> 3351264.5 | V5: =(O5+O4)/2 -> 1943201 | W5: =IFERROR(D5/B5,"") -> 0.91665229 | X5: =IFERROR(E5/B5,"") -> 0.23582736 | Y5: =IFERROR(G5/B5,"") -> 0.24399227 | Z5: =IFERROR(G5/T5,"") -> 0.19166651 | AA5: =IFERROR(G5/U5,"") -> 0.22743535 | AB5: =IFERROR(J5/M5,"") -> 13.04341 | AC5: =IFERROR((J5-Q5)/M5,"") -> 13.034401 | AD5: =IFERROR(N5/M5,"") -> 0.17038483 | AE5: =IFERROR(K5/H5,"") -> 0.78950435 | AF5: =IFERROR(R5/K5,"") -> 0.26661747 | AG5: =IFERROR(R5/H5,"") -> 0.21049565 | AH5: =IFERROR(B5/T5,"") -> 0.78554336 | AI5: =IFERROR(V5/B5*365,"") -> 227.04921 | AJ5: =IFERROR(B5/B4-1,"") -> 0.22935712 | AK5: =IFERROR(G5/G4-1,"") -> -2.7808859 | AL5: =IFERROR(H5/H4-1,"") -> 0.0034358912
A6: 2024 | B6: =SUMIFS(clean_financials_2020_2025!$D:$D,clean_financials_2020_2025!$C:$C,$A6,clean_financials_2020_2025!$B:$B,2110,clean_financials_2020_2025!$E:$E,"income_statement") -> 3520647 | C6: =SUMIFS(clean_financials_2020_2025!$D:$D,clean_financials_2020_2025!$C:$C,$A6,clean_financials_2020_2025!$B:$B,2120,clean_financials_2020_2025!$E:$E,"income_statement") -> -277604 | D6: =SUMIFS(clean_financials_2020_2025!$D:$D,clean_financials_2020_2025!$C:$C,$A6,clean_financials_2020_2025!$B:$B,2100,clean_financials_2020_2025!$E:$E,"income_statement") -> 3243043 | E6: =SUMIFS(clean_financials_2020_2025!$D:$D,clean_financials_2020_2025!$C:$C,$A6,clean_financials_2020_2025!$B:$B,2200,clean_financials_2020_2025!$E:$E,"income_statement") -> 825793 | F6: =SUMIFS(clean_financials_2020_2025!$D:$D,clean_financials_2020_2025!$C:$C,$A6,clean_financials_2020_2025!$B:$B,2300,clean_financials_2020_2025!$E:$E,"income_statement") -> 9618 | G6: =SUMIFS(clean_financials_2020_2025!$D:$D,clean_financials_2020_2025!$C:$C,$A6,clean_financials_2020_2025!$B:$B,2400,clean_financials_2020_2025!$E:$E,"income_statement") -> -155403 | H6: =SUMIFS(clean_financials_2020_2025!$D:$D,clean_financials_2020_2025!$C:$C,$A6,clean_financials_2020_2025!$B:$B,1600,clean_financials_2020_2025!$E:$E,"balance") -> 4287479 | I6: =SUMIFS(clean_financials_2020_2025!$D:$D,clean_financials_2020_2025!$C:$C,$A6,clean_financials_2020_2025!$B:$B,1100,clean_financials_2020_2025!$E:$E,"balance") -> 266946 | J6: =SUMIFS(clean_financials_2020_2025!$D:$D,clean_financials_2020_2025!$C:$C,$A6,clean_financials_2020_2025!$B:$B,1200,clean_financials_2020_2025!$E:$E,"balance") -> 4020533 | K6: =SUMIFS(clean_financials_2020_2025!$D:$D,clean_financials_2020_2025!$C:$C,$A6,clean_financials_2020_2025!$B:$B,1300,clean_financials_2020_2025!$E:$E,"balance") -> 2914586 | L6: =SUMIFS(clean_financials_2020_2025!$D:$D,clean_financials_2020_2025!$C:$C,$A6,clean_financials_2020_2025!$B:$B,1400,clean_financials_2020_2025!$E:$E,"balance") -> 633626 | M6: =SUMIFS(clean_financials_2020_2025!$D:$D,clean_financials_2020_2025!$C:$C,$A6,clean_financials_2020_2025!$B:$B,1500,clean_financials_2020_2025!$E:$E,"balance") -> 739267 | N6: =SUMIFS(clean_financials_2020_2025!$D:$D,clean_financials_2020_2025!$C:$C,$A6,clean_financials_2020_2025!$B:$B,1250,clean_financials_2020_2025!$E:$E,"balance") -> 39658 | O6: =SUMIFS(clean_financials_2020_2025!$D:$D,clean_financials_2020_2025!$C:$C,$A6,clean_financials_2020_2025!$B:$B,1230,clean_financials_2020_2025!$E:$E,"balance") -> 3273651 | P6: =SUMIFS(clean_financials_2020_2025!$D:$D,clean_financials_2020_2025!$C:$C,$A6,clean_financials_2020_2025!$B:$B,1520,clean_financials_2020_2025!$E:$E,"balance") -> 666648 | Q6: =SUMIFS(clean_financials_2020_2025!$D:$D,clean_financials_2020_2025!$C:$C,$A6,clean_financials_2020_2025!$B:$B,1210,clean_financials_2020_2025!$E:$E,"balance") -> 2179 | R6: =L6+M6 -> 1372893 | S6: =J6-M6 -> 3281266 | T6: =(H6+H5)/2 -> 4135488.5 | U6: =(K6+K5)/2 -> 3029787.5 | V6: =(O6+O5)/2 -> 2803339.5 | W6: =IFERROR(D6/B6,"") -> 0.92114972 | X6: =IFERROR(E6/B6,"") -> 0.23455717 | Y6: =IFERROR(G6/B6,"") -> -0.044140466 | Z6: =IFERROR(G6/T6,"") -> -0.037577906 | AA6: =IFERROR(G6/U6,"") -> -0.051291716 | AB6: =IFERROR(J6/M6,"") -> 5.4385398 | AC6: =IFERROR((J6-Q6)/M6,"") -> 5.4355923 | AD6: =IFERROR(N6/M6,"") -> 0.053645029 | AE6: =IFERROR(K6/H6,"") -> 0.67979015 | AF6: =IFERROR(R6/K6,"") -> 0.4710422 | AG6: =IFERROR(R6/H6,"") -> 0.32020985 | AH6: =IFERROR(B6/T6,"") -> 0.85132554 | AI6: =IFERROR(V6/B6*365,"") -> 290.63377 | AJ6: =IFERROR(B6/B5-1,"") -> 0.1270207 | AK6: =IFERROR(G6/G5-1,"") -> -1.2038885 | AL6: =IFERROR(H6/H5-1,"") -> 0.076310067
A7: 2025 | B7: =SUMIFS(clean_financials_2020_2025!$D:$D,clean_financials_2020_2025!$C:$C,$A7,clean_financials_2020_2025!$B:$B,2110,clean_financials_2020_2025!$E:$E,"income_statement") -> 3589154 | C7: =SUMIFS(clean_financials_2020_2025!$D:$D,clean_financials_2020_2025!$C:$C,$A7,clean_financials_2020_2025!$B:$B,2120,clean_financials_2020_2025!$E:$E,"income_statement") -> -2038969 | D7: =SUMIFS(clean_financials_2020_2025!$D:$D,clean_financials_2020_2025!$C:$C,$A7,clean_financials_2020_2025!$B:$B,2100,clean_financials_2020_2025!$E:$E,"income_statement") -> 1550185 | E7: =SUMIFS(clean_financials_2020_2025!$D:$D,clean_financials_2020_2025!$C:$C,$A7,clean_financials_2020_2025!$B:$B,2200,clean_financials_2020_2025!$E:$E,"income_statement") -> 591644 | F7: =SUMIFS(clean_financials_2020_2025!$D:$D,clean_financials_2020_2025!$C:$C,$A7,clean_financials_2020_2025!$B:$B,2300,clean_financials_2020_2025!$E:$E,"income_statement") -> 247040 | G7: =SUMIFS(clean_financials_2020_2025!$D:$D,clean_financials_2020_2025!$C:$C,$A7,clean_financials_2020_2025!$B:$B,2400,clean_financials_2020_2025!$E:$E,"income_statement") -> -375492 | H7: =SUMIFS(clean_financials_2020_2025!$D:$D,clean_financials_2020_2025!$C:$C,$A7,clean_financials_2020_2025!$B:$B,1600,clean_financials_2020_2025!$E:$E,"balance") -> 5948756 | I7: =SUMIFS(clean_financials_2020_2025!$D:$D,clean_financials_2020_2025!$C:$C,$A7,clean_financials_2020_2025!$B:$B,1100,clean_financials_2020_2025!$E:$E,"balance") -> 1209200 | J7: =SUMIFS(clean_financials_2020_2025!$D:$D,clean_financials_2020_2025!$C:$C,$A7,clean_financials_2020_2025!$B:$B,1200,clean_financials_2020_2025!$E:$E,"balance") -> 4739556 | K7: =SUMIFS(clean_financials_2020_2025!$D:$D,clean_financials_2020_2025!$C:$C,$A7,clean_financials_2020_2025!$B:$B,1300,clean_financials_2020_2025!$E:$E,"balance") -> 2539094 | L7: =SUMIFS(clean_financials_2020_2025!$D:$D,clean_financials_2020_2025!$C:$C,$A7,clean_financials_2020_2025!$B:$B,1400,clean_financials_2020_2025!$E:$E,"balance") -> 2067866 | M7: =SUMIFS(clean_financials_2020_2025!$D:$D,clean_financials_2020_2025!$C:$C,$A7,clean_financials_2020_2025!$B:$B,1500,clean_financials_2020_2025!$E:$E,"balance") -> 1341796 | N7: =SUMIFS(clean_financials_2020_2025!$D:$D,clean_financials_2020_2025!$C:$C,$A7,clean_financials_2020_2025!$B:$B,1250,clean_financials_2020_2025!$E:$E,"balance") -> 9374 | O7: =SUMIFS(clean_financials_2020_2025!$D:$D,clean_financials_2020_2025!$C:$C,$A7,clean_financials_2020_2025!$B:$B,1230,clean_financials_2020_2025!$E:$E,"balance") -> 4661132 | P7: =SUMIFS(clean_financials_2020_2025!$D:$D,clean_financials_2020_2025!$C:$C,$A7,clean_financials_2020_2025!$B:$B,1520,clean_financials_2020_2025!$E:$E,"balance") -> 1228249 | Q7: =SUMIFS(clean_financials_2020_2025!$D:$D,clean_financials_2020_2025!$C:$C,$A7,clean_financials_2020_2025!$B:$B,1210,clean_financials_2020_2025!$E:$E,"balance") -> 2615 | R7: =L7+M7 -> 3409662 | S7: =J7-M7 -> 3397760 | T7: =(H7+H6)/2 -> 5118117.5 | U7: =(K7+K6)/2 -> 2726840 | V7: =(O7+O6)/2 -> 3967391.5 | W7: =IFERROR(D7/B7,"") -> 0.43190819 | X7: =IFERROR(E7/B7,"") -> 0.16484219 | Y7: =IFERROR(G7/B7,"") -> -0.10461853 | Z7: =IFERROR(G7/T7,"") -> -0.073365256 | AA7: =IFERROR(G7/U7,"") -> -0.13770225 | AB7: =IFERROR(J7/M7,"") -> 3.5322478 | AC7: =IFERROR((J7-Q7)/M7,"") -> 3.5302989 | AD7: =IFERROR(N7/M7,"") -> 0.0069861588 | AE7: =IFERROR(K7/H7,"") -> 0.42682773 | AF7: =IFERROR(R7/K7,"") -> 1.3428656 | AG7: =IFERROR(R7/H7,"") -> 0.57317227 | AH7: =IFERROR(B7/T7,"") -> 0.70126448 | AI7: =IFERROR(V7/B7*365,"") -> 403.46497 | AJ7: =IFERROR(B7/B6-1,"") -> 0.019458639 | AK7: =IFERROR(G7/G6-1,"") -> 1.4162468 | AL7: =IFERROR(H7/H6-1,"") -> 0.38747175

Sheet clean_financials_2020_2025
A1: line_name | B1: line_code | C1: year | D1: value | E1: statement
A2: Итого по разделу I | B2: 1100 | C2: 2020 | D2: 268300 | E2: balance
A3: Итого по разделу I | B3: 1100 | C3: 2021 | D3: 343275 | E3: balance
A4: Итого по разделу I | B4: 1100 | C4: 2022 | D4: 288795 | E4: balance
A5: Итого по разделу I | B5: 1100 | C5: 2023 | D5: 743254 | E5: balance
A6: Итого по разделу I | B6: 1100 | C6: 2024 | D6: 266946 | E6: balance
A7: Итого по разделу I | B7: 1100 | C7: 2025 | D7: 1209200 | E7: balance
A8: Нематериальные активы | B8: 1110 | C8: 2020 | D8: 56507 | E8: balance
A9: Нематериальные активы | B9: 1110 | C9: 2021 | D9: 49737 | E9: balance
A10: Нематериальные активы | B10: 1110 | C10: 2022 | D10: 26219 | E10: balance
A11: Нематериальные активы | B11: 1110 | C11: 2023 | D11: 26715 | E11: balance
A12: Нематериальные активы | B12: 1110 | C12: 2024 | D12: 23544 | E12: balance
A13: Нематериальные активы | B13: 1110 | C13: 2025 | D13: 25012 | E13: balance
... A277: Совокупный финансовый результат | B277: 2500 | C277: 2025 | D277: -375492 | E277: income_statement

Sheet clean_balance_2020_2025
A1: line_name | B1: line_code | C1: year | D1: value | E1: statement
A2: Итого по разделу I | B2: 1100 | C2: 2020 | D2: 268300 | E2: balance
A3: Итого по разделу I | B3: 1100 | C3: 2021 | D3: 343275 | E3: balance
A4: Итого по разделу I | B4: 1100 | C4: 2022 | D4: 288795 | E4: balance
A5: Итого по разделу I | B5: 1100 | C5: 2023 | D5: 743254 | E5: balance
A6: Итого по разделу I | B6: 1100 | C6: 2024 | D6: 266946 | E6: balance
A7: Итого по разделу I | B7: 1100 | C7: 2025 | D7: 1209200 | E7: balance
A8: Нематериальные активы | B8: 1110 | C8: 2020 | D8: 56507 | E8: balance
A9: Нематериальные активы | B9: 1110 | C9: 2021 | D9: 49737 | E9: balance
A10: Нематериальные активы | B10: 1110 | C10: 2022 | D10: 26219 | E10: balance
A11: Нематериальные активы | B11: 1110 | C11: 2023 | D11: 26715 | E11: balance
A12: Нематериальные активы | B12: 1110 | C12: 2024 | D12: 23544 | E12: balance
A13: Нематериальные активы | B13: 1110 | C13: 2025 | D13: 25012 | E13: balance
... A169: БАЛАНС(пассив) | B169: 1700 | C169: 2025 | D169: 5948756 | E169: balance

Sheet clean_income_statement_2020_202
A1: line_name | B1: line_code | C1: year | D1: value | E1: statement
A2: Валовая прибыль (убыток) | B2: 2100 | C2: 2020 | D2: 1741707 | E2: income_statement
A3: Валовая прибыль (убыток) | B3: 2100 | C3: 2021 | D3: 1881930 | E3: income_statement
A4: Валовая прибыль (убыток) | B4: 2100 | C4: 2022 | D4: 2019923 | E4: income_statement
A5: Валовая прибыль (убыток) | B5: 2100 | C5: 2023 | D5: 2863487 | E5: income_statement
A6: Валовая прибыль (убыток) | B6: 2100 | C6: 2024 | D6: 3243043 | E6: income_statement
A7: Валовая прибыль (убыток) | B7: 2100 | C7: 2025 | D7: 1550185 | E7: income_statement
A8: Выручка | B8: 2110 | C8: 2020 | D8: 2536151 | E8: income_statement
A9: Выручка | B9: 2110 | C9: 2021 | D9: 2532640 | E9: income_statement
A10: Выручка | B10: 2110 | C10: 2022 | D10: 2541046 | E10: income_statement
A11: Выручка | B11: 2110 | C11: 2023 | D11: 3123853 | E11: income_statement
A12: Выручка | B12: 2110 | C12: 2024 | D12: 3520647 | E12: income_statement
A13: Выручка | B13: 2110 | C13: 2025 | D13: 3589154 | E13: income_statement
... A109: Совокупный финансовый результат | B109: 2500 | C109: 2025 | D109: -375492 | E109: income_statement

Sheet 2023-2025
A1: line_name | B1: line_code | C1: year | D1: value | E1: statement
A2: Нематериальные активы | B2: 1110 | C2: 2023 | D2: 26715 | E2: balance
A3: Нематериальные активы | B3: 1110 | C3: 2024 | D3: 23544 | E3: balance
A4: Нематериальные активы | B4: 1110 | C4: 2025 | D4: 25012 | E4: balance
A5: Основные средства | B5: 1150 | C5: 2023 | D5: 96149 | E5: balance
A6: Основные средства | B6: 1150 | C6: 2024 | D6: 201725 | E6: balance
A7: Основные средства | B7: 1150 | C7: 2025 | D7: 429022 | E7: balance
A8: Инвестиционная недвижимость | B8: 1160 | C8: 2023 | D8: 0 | E8: balance
A9: Инвестиционная недвижимость | B9: 1160 | C9: 2024 | D9: 0 | E9: balance
A10: Инвестиционная недвижимость | B10: 1160 | C10: 2025 | D10: 0 | E10: balance
A11: Финансовые вложения | B11: 1170 | C11: 2023 | D11: 613266 | E11: balance
A12: Финансовые вложения | B12: 1170 | C12: 2024 | D12: 13313 | E12: balance
A13: Финансовые вложения | B13: 1170 | C13: 2025 | D13: 703120 | E13: balance
... A85: БАЛАНС(пассив) | B85: 1700 | C85: 2025 | D85: 5948756 | E85: balance

Sheet 2020-2022
A1: line_name | B1: line_code | C1: year | D1: value | E1: statement
A2: Нематериальные активы | B2: 1110 | C2: 2020 | D2: 56507 | E2: balance
A3: Нематериальные активы | B3: 1110 | C3: 2021 | D3: 49737 | E3: balance
A4: Нематериальные активы | B4: 1110 | C4: 2022 | D4: 26219 | E4: balance
A5: Основные средства | B5: 1150 | C5: 2020 | D5: 90852 | E5: balance
A6: Основные средства | B6: 1150 | C6: 2021 | D6: 162270 | E6: balance
A7: Основные средства | B7: 1150 | C7: 2022 | D7: 148762 | E7: balance
A8: Доходные вложения в материальные ценности | B8: 1160 | C8: 2020 | D8: 0 | E8: balance
A9: Доходные вложения в материальные ценности | B9: 1160 | C9: 2021 | D9: 1213 | E9: balance
A10: Доходные вложения в материальные ценности | B10: 1160 | C10: 2022 | D10: 1213 | E10: balance
A11: Финансовые вложения | B11: 1170 | C11: 2020 | D11: 113733 | E11: balance
A12: Финансовые вложения | B12: 1170 | C12: 2021 | D12: 126685 | E12: balance
A13: Финансовые вложения | B13: 1170 | C13: 2022 | D13: 112601 | E13: balance
... A85: БАЛАНС | B85: 1700 | C85: 2022 | D85: 3969858 | E85: balance

Sheet офр_24_25
A1: line_name | B1: line_code | C1: year | D1: value | E1: statement
A2: Выручка | B2: 2110 | C2: 2024 | D2: 3520647 | E2: income_statement
A3: Выручка | B3: 2110 | C3: 2025 | D3: 3589154 | E3: income_statement
A4: Себестоимость продаж | B4: 2120 | C4: 2024 | D4: -277604 | E4: income_statement
A5: Себестоимость продаж | B5: 2120 | C5: 2025 | D5: -2038969 | E5: income_statement
A6: Валовая прибыль (убыток) | B6: 2100 | C6: 2024 | D6: 3243043 | E6: income_statement
A7: Валовая прибыль (убыток) | B7: 2100 | C7: 2025 | D7: 1550185 | E7: income_statement
A8: Коммерческие расходы | B8: 2210 | C8: 2024 | D8: -3 | E8: income_statement
A9: Коммерческие расходы | B9: 2210 | C9: 2025 | D9: -7 | E9: income_statement
A10: Управленческие расходы | B10: 2220 | C10: 2024 | D10: -2417247 | E10: income_statement
A11: Управленческие расходы | B11: 2220 | C11: 2025 | D11: -958534 | E11: income_statement
A12: Прибыль (убыток) от продаж | B12: 2200 | C12: 2024 | D12: 825793 | E12: income_statement
A13: Прибыль (убыток) от продаж | B13: 2200 | C13: 2025 | D13: 591644 | E13: income_statement
... A37: Совокупный финансовый результат | B37: 2500 | C37: 2025 | D37: -375492 | E37: income_statement

Sheet офр_22_23
A1: line_name | B1: line_code | C1: year | D1: value | E1: statement
A2: Выручка | B2: 2110 | C2: 2022 | D2: 2541046 | E2: income_statement
A3: Выручка | B3: 2110 | C3: 2023 | D3: 3123853 | E3: income_statement
A4: Себестоимость продаж | B4: 2120 | C4: 2022 | D4: -521123 | E4: income_statement
A5: Себестоимость продаж | B5: 2120 | C5: 2023 | D5: -260366 | E5: income_statement
A6: Валовая прибыль (убыток) | B6: 2100 | C6: 2022 | D6: 2019923 | E6: income_statement
A7: Валовая прибыль (убыток) | B7: 2100 | C7: 2023 | D7: 2863487 | E7: income_statement
A8: Коммерческие расходы | B8: 2210 | C8: 2022 | D8: -5 | E8: income_statement
A9: Коммерческие расходы | B9: 2210 | C9: 2023 | D9: -6 | E9: income_statement
A10: Управленческие расходы | B10: 2220 | C10: 2022 | D10: -1248923 | E10: income_statement
A11: Управленческие расходы | B11: 2220 | C11: 2023 | D11: -2126791 | E11: income_statement
A12: Прибыль (убыток) от продаж | B12: 2200 | C12: 2022 | D12: 770995 | E12: income_statement
A13: Прибыль (убыток) от продаж | B13: 2200 | C13: 2023 | D13: 736690 | E13: income_statement
... A37: Совокупный финансовый результат | B37: 2500 | C37: 2023 | D37: 762196 | E37: income_statement

Sheet офр_20_21
A1: line_name | B1: line_code | C1: year | D1: value | E1: statement
A2: Выручка | B2: 2110 | C2: 2020 | D2: 2536151 | E2: income_statement
A3: Выручка | B3: 2110 | C3: 2021 | D3: 2532640 | E3: income_statement
A4: Себестоимость продаж | B4: 2120 | C4: 2020 | D4: -794444 | E4: income_statement
A5: Себестоимость продаж | B5: 2120 | C5: 2021 | D5: -650710 | E5: income_statement
A6: Валовая прибыль (убыток) | B6: 2100 | C6: 2020 | D6: 1741707 | E6: income_statement
A7: Валовая прибыль (убыток) | B7: 2100 | C7: 2021 | D7: 1881930 | E7: income_statement
A8: Коммерческие расходы | B8: 2210 | C8: 2020 | D8: -124 | E8: income_statement
A9: Коммерческие расходы | B9: 2210 | C9: 2021 | D9: -9 | E9: income_statement
A10: Управленческие расходы | B10: 2220 | C10: 2020 | D10: -678736 | E10: income_statement
A11: Управленческие расходы | B11: 2220 | C11: 2021 | D11: -904581 | E11: income_statement
A12: Прибыль (убыток) от продаж | B12: 2200 | C12: 2020 | D12: 1062847 | E12: income_statement
A13: Прибыль (убыток) от продаж | B13: 2200 | C13: 2021 | D13: 977340 | E13: income_statement
... A37: Совокупный финансовый результат | B37: 2500 | C37: 2021 | D37: 1033647 | E37: income_statement
